regex_engine/__init__.py
regex_engine/regex_generator.py
regex_engine-1.1.0.dist-info/LICENSE
regex_engine-1.1.0.dist-info/METADATA
regex_engine-1.1.0.dist-info/WHEEL
regex_engine-1.1.0.dist-info/top_level.txt
regex_engine-1.1.0.dist-info/RECORD
