Metadata-Version: 2.1
Name: regex-engine
Version: 1.1.0
Summary: Generate regex using python that can fit your needs
Home-page: https://github.com/raj-kiran-p/regex_engine
Author: Raj Kiran P
Author-email: rajkiranjp@gmail.com
License: UNKNOWN
Platform: UNKNOWN
Classifier: Programming Language :: Python :: 3
Classifier: License :: OSI Approved :: MIT License
Classifier: Operating System :: OS Independent
Requires-Python: >=3.6
